py_unite_db/__init__.py
py_unite_db/api_base.py
py_unite_db/models/__init__.py
py_unite_db/models/base_model.py
py_unite_db/models/battle_item.py
py_unite_db/models/held_item.py
py_unite_db/models/item.py
py_unite_db/models/pokemon.py
py_unite_db/models/stats.py
py_unite_db/py.typed
py_unite_db/types.py
py_unite_db/unite_db.py
py_unite_db/utils.py
py_unite_db-0.3.0.dist-info/WHEEL
py_unite_db-0.3.0.dist-info/METADATA
py_unite_db-0.3.0.dist-info/licenses/LICENSE
py_unite_db-0.3.0.dist-info/RECORD
